c19/__init__.py
c19/c19.py
c19/countries/__init__.py
c19/countries/gb.py
c19/countries/pk.py
c19-0.0.7.dist-info/METADATA
c19-0.0.7.dist-info/WHEEL
c19-0.0.7.dist-info/top_level.txt
c19-0.0.7.dist-info/RECORD
