Metadata-Version: 2.1
Name: c19
Version: 0.0.7
Summary: COVID-19 stats package for the country of Pakistan.
Author: siphr
Author-email: pypi@techtum.dev
License: UNKNOWN
Project-URL: Homepage, https://www.techtum.dev/work-c19-220109.html
Project-URL: Source, https://github.com/siphr/c19
Project-URL: Tracker, https://github.com/siphr/c19/issues
Keywords: covid-19,stats,distribution,Pakistan
Platform: any
